aztec_tool/__init__.py
aztec_tool/__main__.py
aztec_tool/codewords.py
aztec_tool/decoder.py
aztec_tool/detection.py
aztec_tool/enums.py
aztec_tool/exceptions.py
aztec_tool/matrix.py
aztec_tool/mode.py
aztec_tool/orientation.py
aztec_tool/tables.py
aztec_tool-0.1.4.dist-info/licenses/LICENSE
aztec_tool-0.1.4.dist-info/METADATA
aztec_tool-0.1.4.dist-info/WHEEL
aztec_tool-0.1.4.dist-info/entry_points.txt
aztec_tool-0.1.4.dist-info/top_level.txt
aztec_tool-0.1.4.dist-info/RECORD
