Metadata-Version: 2.4
Name: aztec_tool
Version: 0.1.4
Summary: A fast, pure-Python Aztec Code reader with auto-orientation and Reed-Solomon correction.
Author-email: Martin Devolder <martin.devolder2@gmail.com>
License: MIT License
Project-URL: Homepage, https://github.com/mdevolde/aztec_tool.git
Project-URL: Documentation, https://github.com/mdevolde/aztec_tool/blob/master/README.md
Project-URL: Repository, https://github.com/mdevolde/aztec_tool.git
Project-URL: Issues, https://github.com/mdevolde/aztec_tool/issues
Project-URL: Changelog, https://github.com/mdevolde/aztec_tool/blob/master/CHANGELOG.md
Keywords: aztec,barcode,decoder,2d barcode,image recognition,aztec code
Classifier: Programming Language :: Python :: 3
Classifier: Programming Language :: Python :: 3.9
Classifier: Programming Language :: Python :: 3.10
Classifier: Programming Language :: Python :: 3.11
Classifier: Programming Language :: Python :: 3.12
Classifier: Programming Language :: Python :: 3.13
Classifier: License :: OSI Approved :: MIT License
Classifier: Operating System :: OS Independent
Classifier: Topic :: Multimedia :: Graphics :: Capture :: Scanners
Classifier: Topic :: Software Development :: Libraries :: Python Modules
Requires-Python: >=3.9
License-File: LICENSE
Requires-Dist: numpy
Requires-Dist: opencv-python
Requires-Dist: reedsolo
Requires-Dist: toml
Provides-Extra: dev
Requires-Dist: black; extra == "dev"
Requires-Dist: pytest>=8.3; extra == "dev"
Requires-Dist: pytest-cov; extra == "dev"
Requires-Dist: ruff; extra == "dev"
Dynamic: license-file
